stratifreg/__init__.py
stratifreg/gmm_groups.py
stratifreg/k_groups.py
stratifreg/two_groups.py
stratifreg/utils.py
statifreg-0.1.1.dist-info/METADATA
statifreg-0.1.1.dist-info/WHEEL
statifreg-0.1.1.dist-info/top_level.txt
statifreg-0.1.1.dist-info/RECORD
