Metadata-Version: 2.4
Name: statifreg
Version: 0.1.1
Summary: A library for fitting regression and gmm models in stratified subsamples with continuity constraints, quantile and lasso.
Author-email: "R. Priam" <rpriam@gmail.com>
Project-URL: Homepage, https://github.com/rpriam/stratifreg-code
Classifier: Development Status :: 4 - Beta
Classifier: Programming Language :: Python :: 3
Requires-Python: >=3.7
